basenet/__init__.py
basenet/vgg16_bn.py
craft/__init__.py
craft_detector/__init__.py
craft_detector/craft.py
craft_detector/craft_utils.py
craft_detector/downloader.py
craft_detector/file_utils.py
craft_detector/imgproc.py
craft_detector/refinenet.py
craft_detector/run_craft.py
craft_detector/test.py
craft_detector/basenet/__init__.py
craft_detector/basenet/vgg16_bn.py
craft_text_detection-0.0.2.dist-info/LICENSE
craft_text_detection-0.0.2.dist-info/METADATA
craft_text_detection-0.0.2.dist-info/WHEEL
craft_text_detection-0.0.2.dist-info/top_level.txt
craft_text_detection-0.0.2.dist-info/RECORD
