Metadata-Version: 2.1
Name: craft-text-detection
Version: 0.0.2
Summary: Official implementation of Character Region Awareness for Text Detection (CRAFT)
Home-page: https://github.com/arj7192/CRAFT-pytorch
Author: Clova AI Research, NAVER Corp., Ashish Jha
Author-email: youngmin.baek@navercorp.com, arj7192@gmail.com
License: UNKNOWN
Platform: UNKNOWN
Classifier: Programming Language :: Python :: 3
Classifier: License :: OSI Approved :: MIT License
Classifier: Operating System :: OS Independent
Requires-Python: >=3.6
Requires-Dist: torch (==0.4.1)
Requires-Dist: torchvision (==0.2.1)
Requires-Dist: opencv-python (==3.4.2.17)
Requires-Dist: scikit-image (==0.14.2)
Requires-Dist: scipy (==1.1.0)
Requires-Dist: pillow (==6.2.0)
Requires-Dist: requests (==2.22.0)
